Metadata-Version: 2.1
Name: outlines_ocr_guidance
Version: 0.1.1
Summary: outlines LLM guide to return YAML-structured spans from texts, typically OCRs from old registries.
Home-page: https://github.com/prhbrt/outlines-ocr-guidance/
Author: H.T. Kruitbosch
Author-email: Herbert Kruitbosch <outlines-ocr-guidance@prinsherbert.nl>
Project-URL: Homepage, https://github.com/prhbrt/outlines-ocr-guidance
Project-URL: Issues, https://github.com/prhbrt/outlines-ocr-guidance/issues
Classifier: Programming Language :: Python :: 3
Classifier: License :: OSI Approved :: MIT License
Classifier: Operating System :: OS Independent
Requires-Python: >=3.0
License-File: LICENSE.txt
